pytouchline_extended/__init__.py
pytouchline_extended-0.4.6.dist-info/licenses/LICENSE
pytouchline_extended-0.4.6.dist-info/METADATA
pytouchline_extended-0.4.6.dist-info/WHEEL
pytouchline_extended-0.4.6.dist-info/top_level.txt
pytouchline_extended-0.4.6.dist-info/RECORD
