Metadata-Version: 2.4
Name: pytouchline_extended
Version: 0.4.6
Summary: A Roth Touchline interface library
Home-page: https://github.com/brondum/pytouchline
Author: Peter Brondum
License: MIT
Keywords: Roth,Touchline,Home Assistant,hassio,Heat pump
Classifier: Development Status :: 3 - Alpha
Classifier: Intended Audience :: Developers
Classifier: License :: OSI Approved :: MIT License
Classifier: Programming Language :: Python :: 3
License-File: LICENSE
Requires-Dist: httplib2
Requires-Dist: faust-cchardet
Dynamic: author
Dynamic: classifier
Dynamic: description
Dynamic: home-page
Dynamic: keywords
Dynamic: license
Dynamic: license-file
Dynamic: requires-dist
Dynamic: summary
